{
  "dashboard": {
    "title": "Kamachess Bot Dashboard",
    "tags": ["kamachess", "telegram", "bot"],
    "timezone": "browser",
    "schemaVersion": 27,
    "version": 1,
    "refresh": "30s",
    "panels": [
      {
        "id": 1,
        "title": "System CPU Usage",
        "type": "graph",
        "targets": [
          {
            "expr": "100 - (avg(rate(node_cpu_seconds_total{mode=\"idle\"}[5m])) * 100)",
            "legendFormat": "CPU Usage %"
          }
        ],
        "gridPos": {"h": 8, "w": 12, "x": 0, "y": 0}
      },
      {
        "id": 2,
        "title": "System Memory Usage",
        "type": "graph",
        "targets": [
          {
            "expr": "(1 - (node_memory_MemAvailable_bytes / node_memory_MemTotal_bytes)) * 100",
            "legendFormat": "Memory Usage %"
          }
        ],
        "gridPos": {"h": 8, "w": 12, "x": 12, "y": 0}
      },
      {
        "id": 3,
        "title": "Bot Container Status",
        "type": "stat",
        "targets": [
          {
            "expr": "up{job=\"kamachess-bot\"}",
            "legendFormat": "Bot Status"
          }
        ],
        "gridPos": {"h": 4, "w": 6, "x": 0, "y": 8}
      },
      {
        "id": 4,
        "title": "Nginx Status",
        "type": "stat",
        "targets": [
          {
            "expr": "up{job=\"nginx\"}",
            "legendFormat": "Nginx Status"
          }
        ],
        "gridPos": {"h": 4, "w": 6, "x": 6, "y": 8}
      },
      {
        "id": 5,
        "title": "PostgreSQL Status",
        "type": "stat",
        "targets": [
          {
            "expr": "up{job=\"postgres\"}",
            "legendFormat": "PostgreSQL Status"
          }
        ],
        "gridPos": {"h": 4, "w": 6, "x": 12, "y": 8}
      },
      {
        "id": 6,
        "title": "Disk Usage",
        "type": "graph",
        "targets": [
          {
            "expr": "(node_filesystem_avail_bytes{mountpoint=\"/\"} / node_filesystem_size_bytes{mountpoint=\"/\"}) * 100",
            "legendFormat": "Disk Available %"
          }
        ],
        "gridPos": {"h": 8, "w": 24, "x": 0, "y": 12}
      }
    ]
  }
}
